pipen_report/__init__.py
pipen_report/_patch_copier.py
pipen_report/cli.py
pipen_report/defaults.py
pipen_report/filters.py
pipen_report/frontend/package-lock.json
pipen_report/frontend/package.json
pipen_report/frontend/public/assets/ccs.css
pipen_report/frontend/public/assets/favicon.png
pipen_report/frontend/public/assets/global.css
pipen_report/frontend/public/assets/system.min.js
pipen_report/frontend/public/data/.keep
pipen_report/frontend/public/index.html
pipen_report/frontend/rollup.config.js.jinja
pipen_report/frontend/src/components/DataTable/ColumnSelector.svelte
pipen_report/frontend/src/components/DataTable/DataTable.svelte
pipen_report/frontend/src/components/DataTable/DataTableInner.svelte
pipen_report/frontend/src/components/DataTable/OverflowMenu.svelte
pipen_report/frontend/src/components/DataTable/index.js
pipen_report/frontend/src/components/DataTable/paginate.js
pipen_report/frontend/src/components/Descr.svelte
pipen_report/frontend/src/components/Iframe.svelte
pipen_report/frontend/src/components/Image/Image.svelte
pipen_report/frontend/src/components/Image/ImageDimension.svelte
pipen_report/frontend/src/components/Image/ImageDownload.svelte
pipen_report/frontend/src/components/Image/ImageDownloadList.svelte
pipen_report/frontend/src/components/Image/ImageInner.svelte
pipen_report/frontend/src/components/Image/index.js
pipen_report/frontend/src/components/Math.svelte
pipen_report/frontend/src/components/PageNavButton.svelte
pipen_report/frontend/src/components/Plotly.svelte
pipen_report/frontend/src/components/index.js
pipen_report/frontend/src/data.json
pipen_report/frontend/src/layouts/Footer.svelte
pipen_report/frontend/src/layouts/Header.svelte
pipen_report/frontend/src/layouts/Index.svelte
pipen_report/frontend/src/layouts/ProcCard.svelte
pipen_report/frontend/src/layouts/ProcGroupCard.svelte
pipen_report/frontend/src/layouts/ProcLayout.svelte
pipen_report/frontend/src/layouts/ProcToc.svelte
pipen_report-1.1.0.dist-info/METADATA
pipen_report-1.1.0.dist-info/WHEEL
pipen_report-1.1.0.dist-info/entry_points.txt
pipen_report-1.1.0.dist-info/RECORD
