Metadata-Version: 2.4
Name: pipen-report
Version: 1.1.0
Summary: Report generation system for pipen
License: MIT
Author: pwwang
Author-email: pwwang@pwwang.com
Requires-Python: >=3.9,<4.0
Classifier: License :: OSI Approved :: MIT License
Classifier: Programming Language :: Python :: 3
Classifier: Programming Language :: Python :: 3.9
Classifier: Programming Language :: Python :: 3.10
Classifier: Programming Language :: Python :: 3.11
Classifier: Programming Language :: Python :: 3.12
Classifier: Programming Language :: Python :: 3.13
Classifier: Programming Language :: Python :: 3.14
Provides-Extra: runinfo
Requires-Dist: Markdown (>=3,<4)
Requires-Dist: copier (>=9.5,<10.0)
Requires-Dist: imagesize (>=1.4,<2.0)
Requires-Dist: pipen (==1.1.*)
Requires-Dist: pipen-runinfo (>=1.1,<2.0) ; extra == "runinfo"
Requires-Dist: python-slugify (>=8.0,<9.0)
Project-URL: Homepage, https://github.com/pwwang/pipen-report
Project-URL: Repository, https://github.com/pwwang/pipen-report
